README.rst
setup.py
zebu.py
zebu.egg-info/PKG-INFO
zebu.egg-info/SOURCES.txt
zebu.egg-info/dependency_links.txt
zebu.egg-info/requires.txt
zebu.egg-info/top_level.txt