Metadata-Version: 1.1
Name: zebu
Version: 2017.5.0
Summary: Uber minimalistic message bus using 0MQ
Home-page: https://github.com/3kwa/zebu
Author: Eugene Van den Bulke
Author-email: eugene.vandenbulke@gmail.com
License: BSD
Platform: UNKNOWN
Classifier: Development Status :: 4 - Beta
Classifier: Intended Audience :: Developers
Classifier: License :: OSI Approved :: BSD License
Classifier: Programming Language :: Python :: 3.6
Classifier: Topic :: Software Development :: Libraries
